autoDiffModule/Forward.py
autoDiffModule/Reverse.py
autoDiffModule/__init__.py
code/Forward.py
code/Reverse.py
code/__init__.py
autoDiffModule-1.0.1.dist-info/LICENSE
autoDiffModule-1.0.1.dist-info/METADATA
autoDiffModule-1.0.1.dist-info/WHEEL
autoDiffModule-1.0.1.dist-info/top_level.txt
autoDiffModule-1.0.1.dist-info/RECORD
