Metadata-Version: 2.1
Name: autoDiffModule
Version: 1.0.1
Summary: An automatic differentiation package
Home-page: https://github.com/PST-philz-sushi-tacos/cs107-FinalProject
Author: Christopher Chen, Avriel Epps-Darling, Pawel Nawrocki, Matthew Quesada
Author-email: christopher_chen@college.harvard.edu
License: UNKNOWN
Platform: UNKNOWN
Classifier: Programming Language :: Python :: 3
Classifier: License :: OSI Approved :: MIT License
Classifier: Operating System :: OS Independent
Requires-Python: >=3.6
